django_sendgrid_tracking/__init__.py
django_sendgrid_tracking/admin.py
django_sendgrid_tracking/apps.py
django_sendgrid_tracking/mail.py
django_sendgrid_tracking/models.py
django_sendgrid_tracking/signals.py
django_sendgrid_tracking/urls.py
django_sendgrid_tracking/views.py
django_sendgrid_tracking/migrations/0001_initial.py
django_sendgrid_tracking/migrations/__init__.py
tests/__init__.py
tests/settings.py
tests/storages.py
tests/test_models.py
tests/test_sent_email.py
tests/test_webhook.py
tests/urls.py
tests/views.py
django_sendgrid_tracking-1.0.6.dist-info/LICENSE.md
django_sendgrid_tracking-1.0.6.dist-info/METADATA
django_sendgrid_tracking-1.0.6.dist-info/WHEEL
django_sendgrid_tracking-1.0.6.dist-info/top_level.txt
django_sendgrid_tracking-1.0.6.dist-info/RECORD
