Metadata-Version: 2.1
Name: django-sendgrid-tracking
Version: 1.0.6
Summary: Sendgrid Mail tracking for Django, store sendgrid tracking info into django models.
Home-page: https://github.com/MattFanto/django-sendgrid-tracking
Author: Mattia Fantoni
Author-email: mattia.fantoni@gmail.com
License: MIT
Platform: UNKNOWN
Classifier: Environment :: Web Environment
Classifier: Framework :: Django
Classifier: Intended Audience :: Developers
Classifier: License :: OSI Approved :: MIT License
Classifier: Natural Language :: English
Classifier: Operating System :: OS Independent
Classifier: Programming Language :: Python
Classifier: Programming Language :: Python :: 3
Classifier: Programming Language :: Python :: 3.6
Classifier: Programming Language :: Python :: 3.7
Classifier: Programming Language :: Python :: 3.8
Classifier: Topic :: Communications :: Email
Classifier: Topic :: Software Development :: Libraries :: Python Modules
Requires-Python: >=3.6
Requires-Dist: Django (>=1.11)
Requires-Dist: pybars3
Requires-Dist: django-extensions
Requires-Dist: django-sendgrid-v5 (>=0.9.0)
